sgdrf/__init__.py
sgdrf/cli.py
sgdrf/model.py
sgdrf/sgdrf_config.py
sgdrf/subsample.py
sgdrf-0.2.1.dist-info/LICENSE.txt
sgdrf-0.2.1.dist-info/WHEEL
sgdrf-0.2.1.dist-info/METADATA
sgdrf-0.2.1.dist-info/RECORD
