Metadata-Version: 2.1
Name: sgdrf
Version: 0.2.1
Summary: Python implementation of Streaming Gaussian Dirichlet Random Fields (San Soucie et al. 2023)
Home-page: https://github.com/san-soucie/sgdrf
License: MIT
Keywords: gaussian_process,statistics
Author: John San Soucie
Maintainer: John San Soucie
Requires-Python: >=3.8.1,<4
Classifier: Development Status :: 3 - Alpha
Classifier: Environment :: Console
Classifier: Intended Audience :: Developers
Classifier: License :: OSI Approved :: MIT License
Classifier: Natural Language :: English
Classifier: Operating System :: OS Independent
Classifier: Programming Language :: Python :: 3
Classifier: Programming Language :: Python :: 3.9
Classifier: Programming Language :: Python :: 3.10
Classifier: Programming Language :: Python :: 3 :: Only
Classifier: Programming Language :: Python :: 3.10
Classifier: Programming Language :: Python :: 3.11
Classifier: Programming Language :: Python :: 3.8
Classifier: Programming Language :: Python :: 3.9
Classifier: Topic :: Software Development :: Libraries :: Python Modules
Provides-Extra: all
Requires-Dist: pyro-ppl (>=1.8.6,<2.0.0)
Requires-Dist: torch (>=2.0.1,<3.0.0)
Requires-Dist: typer (>=0.3,<0.10)
Project-URL: CI, https://github.com/san-soucie/sgdrf/actions
Project-URL: Documentation, https://sgdrf.readthedocs.io
Project-URL: Download, https://pypi.org/project/sgdrf/
Project-URL: Issues, https://github.com/san-soucie/sgdrf/issues
Project-URL: Repository, https://github.com/san-soucie/sgdrf
